MANIFEST.in
README.rst
setup.py
cpp/ClassWrapper.h
cpp/ImmutableDict.cpp
cpp/ImmutableDict.h
cpp/ImmutableDictImpl.h
cpp/ImmutableList.cpp
cpp/ImmutableList.h
cpp/ImmutableListImpl.h
cpp/PyObjectRef.h
cpp/Sha1.h
cpp/Sha1Hash.h
cpp/Sha1Hasher.h
cpp/docstrings.txt
cpp/main.cpp
cpp/util.cpp
cpp/util.h
cpp/clinic/ImmutableDict.cpp.h
cpp/clinic/ImmutableList.cpp.h
lib/immer/LICENSE
lib/immer/README.rst
lib/immer/immer/algorithm.hpp
lib/immer/immer/array.hpp
lib/immer/immer/array_transient.hpp
lib/immer/immer/atom.hpp
lib/immer/immer/box.hpp
lib/immer/immer/config.hpp
lib/immer/immer/flex_vector.hpp
lib/immer/immer/flex_vector_transient.hpp
lib/immer/immer/map.hpp
lib/immer/immer/map_transient.hpp
lib/immer/immer/memory_policy.hpp
lib/immer/immer/set.hpp
lib/immer/immer/set_transient.hpp
lib/immer/immer/vector.hpp
lib/immer/immer/vector_transient.hpp
lib/immer/immer/detail/combine_standard_layout.hpp
lib/immer/immer/detail/iterator_facade.hpp
lib/immer/immer/detail/ref_count_base.hpp
lib/immer/immer/detail/type_traits.hpp
lib/immer/immer/detail/util.hpp
lib/immer/immer/detail/arrays/no_capacity.hpp
lib/immer/immer/detail/arrays/node.hpp
lib/immer/immer/detail/arrays/with_capacity.hpp
lib/immer/immer/detail/hamts/bits.hpp
lib/immer/immer/detail/hamts/champ.hpp
lib/immer/immer/detail/hamts/champ_iterator.hpp
lib/immer/immer/detail/hamts/node.hpp
lib/immer/immer/detail/rbts/bits.hpp
lib/immer/immer/detail/rbts/node.hpp
lib/immer/immer/detail/rbts/operations.hpp
lib/immer/immer/detail/rbts/position.hpp
lib/immer/immer/detail/rbts/rbtree.hpp
lib/immer/immer/detail/rbts/rbtree_iterator.hpp
lib/immer/immer/detail/rbts/rrbtree.hpp
lib/immer/immer/detail/rbts/rrbtree_iterator.hpp
lib/immer/immer/detail/rbts/visitor.hpp
lib/immer/immer/experimental/dvektor.hpp
lib/immer/immer/experimental/detail/dvektor_impl.hpp
lib/immer/immer/heap/cpp_heap.hpp
lib/immer/immer/heap/debug_size_heap.hpp
lib/immer/immer/heap/free_list_heap.hpp
lib/immer/immer/heap/free_list_node.hpp
pyimmutable.egg-info/PKG-INFO
pyimmutable.egg-info/SOURCES.txt
pyimmutable.egg-info/dependency_links.txt
pyimmutable.egg-info/top_level.txt