Metadata-Version: 2.1
Name: pyimmutable
Version: 0.2.0
Summary: Immutable dict and lists
Home-page: https://github.com/spacedentist/pyimmutable
Author: Sven Over
Author-email: sp@cedenti.st
License: MIT
Download-URL: https://github.com/spacedentist/pyimmutable/archive/0.2.0.tar.gz
Platform: UNKNOWN
Classifier: Development Status :: 3 - Alpha
Classifier: Programming Language :: Python :: 3
Classifier: License :: OSI Approved :: MIT License
Classifier: Operating System :: OS Independent
